<?xml version="1.0" encoding="utf-8" ?>
<dwsync>
<file name="application.png" server="w4.texus.lt" local="130664834176379171" remote="130664713200000000" Dst="1" />
<file name="code.png" server="w4.texus.lt" local="130664834176468911" remote="130664713200000000" Dst="1" />
<file name="css.png" server="w4.texus.lt" local="130664834176968937" remote="130664713200000000" Dst="1" />
<file name="db.png" server="w4.texus.lt" local="130664834177439004" remote="130664713200000000" Dst="1" />
<file name="directory.png" server="w4.texus.lt" local="130664834178009009" remote="130664713200000000" Dst="1" />
<file name="doc.png" server="w4.texus.lt" local="130664834178539028" remote="130664713200000000" Dst="1" />
<file name="file.png" server="w4.texus.lt" local="130664834178599030" remote="130664713200000000" Dst="1" />
<file name="film.png" server="w4.texus.lt" local="130664834179119061" remote="130664713200000000" Dst="1" />
<file name="flash.png" server="w4.texus.lt" local="130664834179629089" remote="130664713200000000" Dst="1" />
<file name="folder_open.png" server="w4.texus.lt" local="130664834179779100" remote="130664713200000000" Dst="1" />
<file name="html.png" server="w4.texus.lt" local="130664834180279150" remote="130664713200000000" Dst="1" />
<file name="java.png" server="w4.texus.lt" local="130664834180869161" remote="130664713200000000" Dst="1" />
<file name="linux.png" server="w4.texus.lt" local="130664834180939165" remote="130664713200000000" Dst="1" />
<file name="music.png" server="w4.texus.lt" local="130664834181429188" remote="130664713200000000" Dst="1" />
<file name="pdf.png" server="w4.texus.lt" local="130664834182029226" remote="130664713200000000" Dst="1" />
<file name="php.png" server="w4.texus.lt" local="130664834182129350" remote="130664713200000000" Dst="1" />
<file name="picture.png" server="w4.texus.lt" local="130664834182529271" remote="130664713200000000" Dst="1" />
<file name="ppt.png" server="w4.texus.lt" local="130664834183069362" remote="130664713200000000" Dst="1" />
<file name="psd.png" server="w4.texus.lt" local="130664834183179293" remote="130664713200000000" Dst="1" />
<file name="ruby.png" server="w4.texus.lt" local="130664834183549314" remote="130664713200000000" Dst="1" />
<file name="script.png" server="w4.texus.lt" local="130664834184189470" remote="130664713200000000" Dst="1" />
<file name="spinner.gif" server="w4.texus.lt" local="130664834184209426" remote="130664713200000000" Dst="1" />
<file name="txt.png" server="w4.texus.lt" local="130664834184789400" remote="130664713200000000" Dst="1" />
<file name="xls.png" server="w4.texus.lt" local="130664834185339415" remote="130664713200000000" Dst="1" />
<file name="zip.png" server="w4.texus.lt" local="130664834185369418" remote="130664713200000000" Dst="1" />
</dwsync>