<?xml version="1.0" encoding="utf-8" ?>
<dwsync>
<file name="addMultiInput.tpl" server="w4.texus.lt" local="130664833738423829" remote="130664712600000000" Dst="1" />
<file name="addMultiInputTpl.tpl" server="w4.texus.lt" local="130664833739143865" remote="130664712600000000" Dst="1" />
<file name="defaultadmin.tpl" server="w4.texus.lt" local="130664833739173873" remote="130664712600000000" Dst="1" />
<file name="editcontent.tpl" server="w4.texus.lt" local="130664833739663969" remote="130664712600000000" Dst="1" />
<file name="header.tpl" server="w4.texus.lt" local="130664833740223923" remote="130664712600000000" Dst="1" />
<file name="index.html" server="w4.texus.lt" local="130664833740233931" remote="130664712600000000" Dst="1" />
<file name="multiInput.tpl" server="w4.texus.lt" local="130664833740753962" remote="130664712600000000" Dst="1" />
<file name="multiInputTab.tpl" server="w4.texus.lt" local="130664833741353995" remote="130664712600000000" Dst="1" />
<file name="multiInputTplTab.tpl" server="w4.texus.lt" local="130664833741413991" remote="130664712600000000" Dst="1" />
<file name="prefsTab.tpl" server="w4.texus.lt" local="130664833741964026" remote="130664712600000000" Dst="1" />
</dwsync>